celyatrix/__init__.py
celyatrix/celyatrix_agi.py
celyatrix/celyatrix_ami.py
celyatrix-0.1.1.dist-info/METADATA
celyatrix-0.1.1.dist-info/WHEEL
celyatrix-0.1.1.dist-info/top_level.txt
celyatrix-0.1.1.dist-info/RECORD
