Metadata-Version: 2.4
Name: celyatrix
Version: 0.1.1
Summary: Une librairie Python pour se connecter a Asterisk
Author-email: CELYA <celya@celya.fr>
License: MIT
Requires-Python: >=3.7
